firecrawl_toolkit/__init__.py
firecrawl_toolkit/__main__.py
firecrawl_toolkit/server.py
firecrawl_toolkit/data/country_aliases.json
firecrawl_toolkit-0.0.11.dist-info/METADATA
firecrawl_toolkit-0.0.11.dist-info/WHEEL
firecrawl_toolkit-0.0.11.dist-info/entry_points.txt
firecrawl_toolkit-0.0.11.dist-info/top_level.txt
firecrawl_toolkit-0.0.11.dist-info/RECORD
