Metadata-Version: 2.4
Name: firecrawl-toolkit
Version: 0.0.11
Summary: A high-performance, asynchronous MCP server for Firecrawl Search, featuring connection pooling, request retries, and intelligent input parsing.
Author-email: "Joey.Kot" <joey.kot.x@gmail.com>
Keywords: firecrawl,mcp,server,google,search
Requires-Python: >=3.12
Requires-Dist: httpx>=0.28.1
Requires-Dist: h2>=4.2.0
Requires-Dist: dotenv>=0.9.9
Requires-Dist: fastmcp>=2.14.4
